[
  {
    "languages": [
      {
        "name": "TypeScript",
        "total_seconds": 3689.493429,
        "digital": "1:01:29",
        "decimal": "1.02",
        "text": "1 hr 1 min",
        "hours": 1,
        "minutes": 1,
        "seconds": 29,
        "percent": 95.81
      },
      {
        "name": "YAML",
        "total_seconds": 97.267697,
        "digital": "0:01:37",
        "decimal": "0.02",
        "text": "1 min",
        "hours": 0,
        "minutes": 1,
        "seconds": 37,
        "percent": 2.53
      },
      {
        "name": "Other",
        "total_seconds": 32.450418,
        "digital": "0:00:32",
        "decimal": "0.00",
        "text": "32 secs",
        "hours": 0,
        "minutes": 0,
        "seconds": 32,
        "percent": 0.84
      },
      {
        "name": "JSON",
        "total_seconds": 24.525048,
        "digital": "0:00:24",
        "decimal": "0.00",
        "text": "24 secs",
        "hours": 0,
        "minutes": 0,
        "seconds": 24,
        "percent": 0.64
      },
      {
        "name": "JavaScript",
        "total_seconds": 7.077372,
        "digital": "0:00:07",
        "decimal": "0.00",
        "text": "7 secs",
        "hours": 0,
        "minutes": 0,
        "seconds": 7,
        "percent": 0.18
      }
    ],
    "grand_total": {
      "hours": 1,
      "minutes": 4,
      "total_seconds": 3850.813964,
      "digital": "1:04",
      "decimal": "1.07",
      "text": "1 hr 4 mins"
    },
    "editors": [
      {
        "name": "VS Code",
        "total_seconds": 3850.813964,
        "digital": "1:04:10",
        "decimal": "1.07",
        "text": "1 hr 4 mins",
        "hours": 1,
        "minutes": 4,
        "seconds": 10,
        "percent": 100
      }
    ],
    "operating_systems": [
      {
        "name": "Windows",
        "total_seconds": 3850.813964,
        "digital": "1:04:10",
        "decimal": "1.07",
        "text": "1 hr 4 mins",
        "hours": 1,
        "minutes": 4,
        "seconds": 10,
        "percent": 100
      }
    ],
    "categories": [
      {
        "name": "Coding",
        "total_seconds": 3850.813964,
        "digital": "1:04:10",
        "decimal": "1.07",
        "text": "1 hr 4 mins",
        "hours": 1,
        "minutes": 4,
        "seconds": 10,
        "percent": 100
      }
    ],
    "dependencies": [
      {
        "name": "roku-ui",
        "total_seconds": 3689.909796,
        "digital": "1:01:29",
        "decimal": "1.02",
        "text": "1 hr 1 min",
        "hours": 1,
        "minutes": 1,
        "seconds": 29,
        "percent": 14
      },
      {
        "name": "react",
        "total_seconds": 3681.966788,
        "digital": "1:01:21",
        "decimal": "1.02",
        "text": "1 hr 1 min",
        "hours": 1,
        "minutes": 1,
        "seconds": 21,
        "percent": 13.97
      },
      {
        "name": "utils",
        "total_seconds": 3674.807322,
        "digital": "1:01:14",
        "decimal": "1.02",
        "text": "1 hr 1 min",
        "hours": 1,
        "minutes": 1,
        "seconds": 14,
        "percent": 13.94
      },
      {
        "name": "localStorageKeyEnum",
        "total_seconds": 3653.880726,
        "digital": "1:00:53",
        "decimal": "1.00",
        "text": "1 hr",
        "hours": 1,
        "minutes": 0,
        "seconds": 53,
        "percent": 13.86
      },
      {
        "name": "localStorage",
        "total_seconds": 3653.880726,
        "digital": "1:00:53",
        "decimal": "1.00",
        "text": "1 hr",
        "hours": 1,
        "minutes": 0,
        "seconds": 53,
        "percent": 13.86
      },
      {
        "name": "Dashboard",
        "total_seconds": 3653.880726,
        "digital": "1:00:53",
        "decimal": "1.00",
        "text": "1 hr",
        "hours": 1,
        "minutes": 0,
        "seconds": 53,
        "percent": 13.86
      },
      {
        "name": "GithubIcon",
        "total_seconds": 3653.880726,
        "digital": "1:00:53",
        "decimal": "1.00",
        "text": "1 hr",
        "hours": 1,
        "minutes": 0,
        "seconds": 53,
        "percent": 13.86
      },
      {
        "name": "typescript",
        "total_seconds": 23.507832,
        "digital": "0:00:23",
        "decimal": "0.00",
        "text": "23 secs",
        "hours": 0,
        "minutes": 0,
        "seconds": 23,
        "percent": 0.09
      },
      {
        "name": "eslint",
        "total_seconds": 23.507832,
        "digital": "0:00:23",
        "decimal": "0.00",
        "text": "23 secs",
        "hours": 0,
        "minutes": 0,
        "seconds": 23,
        "percent": 0.09
      },
      {
        "name": "@types/react-dom",
        "total_seconds": 23.507832,
        "digital": "0:00:23",
        "decimal": "0.00",
        "text": "23 secs",
        "hours": 0,
        "minutes": 0,
        "seconds": 23,
        "percent": 0.09
      },
      {
        "name": "vite",
        "total_seconds": 23.507832,
        "digital": "0:00:23",
        "decimal": "0.00",
        "text": "23 secs",
        "hours": 0,
        "minutes": 0,
        "seconds": 23,
        "percent": 0.09
      },
      {
        "name": "@types/react",
        "total_seconds": 23.507832,
        "digital": "0:00:23",
        "decimal": "0.00",
        "text": "23 secs",
        "hours": 0,
        "minutes": 0,
        "seconds": 23,
        "percent": 0.09
      },
      {
        "name": "react-dom",
        "total_seconds": 23.507832,
        "digital": "0:00:23",
        "decimal": "0.00",
        "text": "23 secs",
        "hours": 0,
        "minutes": 0,
        "seconds": 23,
        "percent": 0.09
      },
      {
        "name": "npm",
        "total_seconds": 23.507832,
        "digital": "0:00:23",
        "decimal": "0.00",
        "text": "23 secs",
        "hours": 0,
        "minutes": 0,
        "seconds": 23,
        "percent": 0.09
      },
      {
        "name": "@vitejs/plugin-react",
        "total_seconds": 23.507832,
        "digital": "0:00:23",
        "decimal": "0.00",
        "text": "23 secs",
        "hours": 0,
        "minutes": 0,
        "seconds": 23,
        "percent": 0.09
      },
      {
        "name": "types",
        "total_seconds": 20.926596,
        "digital": "0:00:20",
        "decimal": "0.00",
        "text": "20 secs",
        "hours": 0,
        "minutes": 0,
        "seconds": 20,
        "percent": 0.08
      },
      {
        "name": "big",
        "total_seconds": 20.926596,
        "digital": "0:00:20",
        "decimal": "0.00",
        "text": "20 secs",
        "hours": 0,
        "minutes": 0,
        "seconds": 20,
        "percent": 0.08
      },
      {
        "name": "Chart",
        "total_seconds": 16.348366,
        "digital": "0:00:16",
        "decimal": "0.00",
        "text": "16 secs",
        "hours": 0,
        "minutes": 0,
        "seconds": 16,
        "percent": 0.06
      },
      {
        "name": "server",
        "total_seconds": 16.348366,
        "digital": "0:00:16",
        "decimal": "0.00",
        "text": "16 secs",
        "hours": 0,
        "minutes": 0,
        "seconds": 16,
        "percent": 0.06
      },
      {
        "name": "components",
        "total_seconds": 16.348366,
        "digital": "0:00:16",
        "decimal": "0.00",
        "text": "16 secs",
        "hours": 0,
        "minutes": 0,
        "seconds": 16,
        "percent": 0.06
      },
      {
        "name": "charts",
        "total_seconds": 16.348366,
        "digital": "0:00:16",
        "decimal": "0.00",
        "text": "16 secs",
        "hours": 0,
        "minutes": 0,
        "seconds": 16,
        "percent": 0.06
      },
      {
        "name": "shared",
        "total_seconds": 16.348366,
        "digital": "0:00:16",
        "decimal": "0.00",
        "text": "16 secs",
        "hours": 0,
        "minutes": 0,
        "seconds": 16,
        "percent": 0.06
      },
      {
        "name": "echarts",
        "total_seconds": 15.102474,
        "digital": "0:00:15",
        "decimal": "0.00",
        "text": "15 secs",
        "hours": 0,
        "minutes": 0,
        "seconds": 15,
        "percent": 0.06
      },
      {
        "name": "@types/big.js",
        "total_seconds": 15.102474,
        "digital": "0:00:15",
        "decimal": "0.00",
        "text": "15 secs",
        "hours": 0,
        "minutes": 0,
        "seconds": 15,
        "percent": 0.06
      },
      {
        "name": "big.js",
        "total_seconds": 15.102474,
        "digital": "0:00:15",
        "decimal": "0.00",
        "text": "15 secs",
        "hours": 0,
        "minutes": 0,
        "seconds": 15,
        "percent": 0.06
      },
      {
        "name": "@typescript-eslint/eslint-plugin",
        "total_seconds": 15.102474,
        "digital": "0:00:15",
        "decimal": "0.00",
        "text": "15 secs",
        "hours": 0,
        "minutes": 0,
        "seconds": 15,
        "percent": 0.06
      },
      {
        "name": "@types/mocha",
        "total_seconds": 15.102474,
        "digital": "0:00:15",
        "decimal": "0.00",
        "text": "15 secs",
        "hours": 0,
        "minutes": 0,
        "seconds": 15,
        "percent": 0.06
      },
      {
        "name": "eslint-plugin-react-refresh",
        "total_seconds": 15.102474,
        "digital": "0:00:15",
        "decimal": "0.00",
        "text": "15 secs",
        "hours": 0,
        "minutes": 0,
        "seconds": 15,
        "percent": 0.06
      },
      {
        "name": "eslint-plugin-react-hooks",
        "total_seconds": 15.102474,
        "digital": "0:00:15",
        "decimal": "0.00",
        "text": "15 secs",
        "hours": 0,
        "minutes": 0,
        "seconds": 15,
        "percent": 0.06
      },
      {
        "name": "@typescript-eslint/parser",
        "total_seconds": 15.102474,
        "digital": "0:00:15",
        "decimal": "0.00",
        "text": "15 secs",
        "hours": 0,
        "minutes": 0,
        "seconds": 15,
        "percent": 0.06
      },
      {
        "name": "echarts-for-react",
        "total_seconds": 15.102474,
        "digital": "0:00:15",
        "decimal": "0.00",
        "text": "15 secs",
        "hours": 0,
        "minutes": 0,
        "seconds": 15,
        "percent": 0.06
      },
      {
        "name": "react-router-dom",
        "total_seconds": 8.405358,
        "digital": "0:00:08",
        "decimal": "0.00",
        "text": "8 secs",
        "hours": 0,
        "minutes": 0,
        "seconds": 8,
        "percent": 0.03
      },
      {
        "name": "@roku-ui/icons-svg-spinners",
        "total_seconds": 8.405358,
        "digital": "0:00:08",
        "decimal": "0.00",
        "text": "8 secs",
        "hours": 0,
        "minutes": 0,
        "seconds": 8,
        "percent": 0.03
      },
      {
        "name": "@types/react-transition-group",
        "total_seconds": 8.405358,
        "digital": "0:00:08",
        "decimal": "0.00",
        "text": "8 secs",
        "hours": 0,
        "minutes": 0,
        "seconds": 8,
        "percent": 0.03
      },
      {
        "name": "prismjs",
        "total_seconds": 8.405358,
        "digital": "0:00:08",
        "decimal": "0.00",
        "text": "8 secs",
        "hours": 0,
        "minutes": 0,
        "seconds": 8,
        "percent": 0.03
      },
      {
        "name": "@unocss/reset",
        "total_seconds": 8.405358,
        "digital": "0:00:08",
        "decimal": "0.00",
        "text": "8 secs",
        "hours": 0,
        "minutes": 0,
        "seconds": 8,
        "percent": 0.03
      },
      {
        "name": "@types/node",
        "total_seconds": 8.405358,
        "digital": "0:00:08",
        "decimal": "0.00",
        "text": "8 secs",
        "hours": 0,
        "minutes": 0,
        "seconds": 8,
        "percent": 0.03
      },
      {
        "name": "react-test-renderer",
        "total_seconds": 8.405358,
        "digital": "0:00:08",
        "decimal": "0.00",
        "text": "8 secs",
        "hours": 0,
        "minutes": 0,
        "seconds": 8,
        "percent": 0.03
      },
      {
        "name": "d3-color",
        "total_seconds": 8.405358,
        "digital": "0:00:08",
        "decimal": "0.00",
        "text": "8 secs",
        "hours": 0,
        "minutes": 0,
        "seconds": 8,
        "percent": 0.03
      },
      {
        "name": "terser",
        "total_seconds": 8.405358,
        "digital": "0:00:08",
        "decimal": "0.00",
        "text": "8 secs",
        "hours": 0,
        "minutes": 0,
        "seconds": 8,
        "percent": 0.03
      },
      {
        "name": "markdown-to-jsx",
        "total_seconds": 8.405358,
        "digital": "0:00:08",
        "decimal": "0.00",
        "text": "8 secs",
        "hours": 0,
        "minutes": 0,
        "seconds": 8,
        "percent": 0.03
      },
      {
        "name": "@roku-ui/icons-material-symbols",
        "total_seconds": 8.405358,
        "digital": "0:00:08",
        "decimal": "0.00",
        "text": "8 secs",
        "hours": 0,
        "minutes": 0,
        "seconds": 8,
        "percent": 0.03
      },
      {
        "name": "@types/prismjs",
        "total_seconds": 8.405358,
        "digital": "0:00:08",
        "decimal": "0.00",
        "text": "8 secs",
        "hours": 0,
        "minutes": 0,
        "seconds": 8,
        "percent": 0.03
      },
      {
        "name": "vite-plugin-dts",
        "total_seconds": 8.405358,
        "digital": "0:00:08",
        "decimal": "0.00",
        "text": "8 secs",
        "hours": 0,
        "minutes": 0,
        "seconds": 8,
        "percent": 0.03
      },
      {
        "name": "@unocss/preset-typography",
        "total_seconds": 8.405358,
        "digital": "0:00:08",
        "decimal": "0.00",
        "text": "8 secs",
        "hours": 0,
        "minutes": 0,
        "seconds": 8,
        "percent": 0.03
      },
      {
        "name": "unocss",
        "total_seconds": 8.405358,
        "digital": "0:00:08",
        "decimal": "0.00",
        "text": "8 secs",
        "hours": 0,
        "minutes": 0,
        "seconds": 8,
        "percent": 0.03
      },
      {
        "name": "react-element-to-jsx-string",
        "total_seconds": 8.405358,
        "digital": "0:00:08",
        "decimal": "0.00",
        "text": "8 secs",
        "hours": 0,
        "minutes": 0,
        "seconds": 8,
        "percent": 0.03
      },
      {
        "name": "@roku-ui/icons-tabler",
        "total_seconds": 8.405358,
        "digital": "0:00:08",
        "decimal": "0.00",
        "text": "8 secs",
        "hours": 0,
        "minutes": 0,
        "seconds": 8,
        "percent": 0.03
      },
      {
        "name": "react-transition-group",
        "total_seconds": 8.405358,
        "digital": "0:00:08",
        "decimal": "0.00",
        "text": "8 secs",
        "hours": 0,
        "minutes": 0,
        "seconds": 8,
        "percent": 0.03
      },
      {
        "name": "@radix-ui/react-scroll-area",
        "total_seconds": 8.405358,
        "digital": "0:00:08",
        "decimal": "0.00",
        "text": "8 secs",
        "hours": 0,
        "minutes": 0,
        "seconds": 8,
        "percent": 0.03
      },
      {
        "name": "classnames",
        "total_seconds": 8.405358,
        "digital": "0:00:08",
        "decimal": "0.00",
        "text": "8 secs",
        "hours": 0,
        "minutes": 0,
        "seconds": 8,
        "percent": 0.03
      },
      {
        "name": "postcss-nesting",
        "total_seconds": 8.405358,
        "digital": "0:00:08",
        "decimal": "0.00",
        "text": "8 secs",
        "hours": 0,
        "minutes": 0,
        "seconds": 8,
        "percent": 0.03
      },
      {
        "name": "@types/react-test-renderer",
        "total_seconds": 8.405358,
        "digital": "0:00:08",
        "decimal": "0.00",
        "text": "8 secs",
        "hours": 0,
        "minutes": 0,
        "seconds": 8,
        "percent": 0.03
      },
      {
        "name": "@jannchie/eslint-config",
        "total_seconds": 8.405358,
        "digital": "0:00:08",
        "decimal": "0.00",
        "text": "8 secs",
        "hours": 0,
        "minutes": 0,
        "seconds": 8,
        "percent": 0.03
      },
      {
        "name": "@babel/core",
        "total_seconds": 8.405358,
        "digital": "0:00:08",
        "decimal": "0.00",
        "text": "8 secs",
        "hours": 0,
        "minutes": 0,
        "seconds": 8,
        "percent": 0.03
      },
      {
        "name": "jsx-to-string",
        "total_seconds": 8.405358,
        "digital": "0:00:08",
        "decimal": "0.00",
        "text": "8 secs",
        "hours": 0,
        "minutes": 0,
        "seconds": 8,
        "percent": 0.03
      },
      {
        "name": "framer-motion",
        "total_seconds": 8.405358,
        "digital": "0:00:08",
        "decimal": "0.00",
        "text": "8 secs",
        "hours": 0,
        "minutes": 0,
        "seconds": 8,
        "percent": 0.03
      },
      {
        "name": "@unocss/transformer-directives",
        "total_seconds": 8.405358,
        "digital": "0:00:08",
        "decimal": "0.00",
        "text": "8 secs",
        "hours": 0,
        "minutes": 0,
        "seconds": 8,
        "percent": 0.03
      },
      {
        "name": "@types/d3-color",
        "total_seconds": 8.405358,
        "digital": "0:00:08",
        "decimal": "0.00",
        "text": "8 secs",
        "hours": 0,
        "minutes": 0,
        "seconds": 8,
        "percent": 0.03
      },
      {
        "name": "StackedHorizontalBar",
        "total_seconds": 4.57823,
        "digital": "0:00:04",
        "decimal": "0.00",
        "text": "4 secs",
        "hours": 0,
        "minutes": 0,
        "seconds": 4,
        "percent": 0.02
      },
      {
        "name": "DoughnutChart",
        "total_seconds": 4.57823,
        "digital": "0:00:04",
        "decimal": "0.00",
        "text": "4 secs",
        "hours": 0,
        "minutes": 0,
        "seconds": 4,
        "percent": 0.02
      },
      {
        "name": "Wakatime",
        "total_seconds": 4.57823,
        "digital": "0:00:04",
        "decimal": "0.00",
        "text": "4 secs",
        "hours": 0,
        "minutes": 0,
        "seconds": 4,
        "percent": 0.02
      },
      {
        "name": "api",
        "total_seconds": 4.57823,
        "digital": "0:00:04",
        "decimal": "0.00",
        "text": "4 secs",
        "hours": 0,
        "minutes": 0,
        "seconds": 4,
        "percent": 0.02
      }
    ],
    "machines": [
      {
        "name": "meng",
        "total_seconds": 3850.813964,
        "machine_name_id": "018c7190-1479-4dd9-b13c-4d0d60c3b3e8",
        "digital": "1:04:10",
        "decimal": "1.07",
        "text": "1 hr 4 mins",
        "hours": 1,
        "minutes": 4,
        "seconds": 10,
        "percent": 100
      }
    ],
    "projects": [
      {
        "name": "wakatime-dashboard",
        "total_seconds": 3850.813964,
        "digital": "1:04:10",
        "decimal": "1.07",
        "text": "1 hr 4 mins",
        "hours": 1,
        "minutes": 4,
        "seconds": 10,
        "percent": 100
      }
    ],
    "range": {
      "start": "2023-12-15T16:00:00Z",
      "end": "2023-12-16T15:59:59Z",
      "date": "2023-12-16",
      "text": "Sat Dec 16th 2023",
      "timezone": "Asia/Shanghai"
    }
  }
]
