[{"categories":[{"decimal":"1.35","digital":"1:21:26","hours":1,"minutes":21,"name":"Coding","percent":100,"seconds":26,"text":"1 hr 21 mins","total_seconds":4886.404}],"dependencies":[{"decimal":"0.17","digital":"0:10:04","hours":0,"minutes":10,"name":"org.jetbrains","percent":100,"seconds":4,"text":"10 mins","total_seconds":604.402}],"editors":[{"decimal":"1.35","digital":"1:21:26","hours":1,"minutes":21,"name":"IntelliJ","percent":100,"seconds":26,"text":"1 hr 21 mins","total_seconds":4886.404}],"grand_total":{"decimal":"1.35","digital":"1:21","hours":1,"minutes":21,"text":"1 hr 21 mins","total_seconds":4886.404},"languages":[{"decimal":"1.12","digital":"1:07:47","hours":1,"minutes":7,"name":"Kotlin","percent":83.24,"seconds":47,"text":"1 hr 7 mins","total_seconds":4067.64},{"decimal":"0.10","digital":"0:06:15","hours":0,"minutes":6,"name":"YAML","percent":7.68,"seconds":15,"text":"6 mins","total_seconds":375.372},{"decimal":"0.05","digital":"0:03:29","hours":0,"minutes":3,"name":"Markdown","percent":4.29,"seconds":29,"text":"3 mins","total_seconds":209.581},{"decimal":"0.03","digital":"0:02:03","hours":0,"minutes":2,"name":"Properties","percent":2.52,"seconds":3,"text":"2 mins","total_seconds":123.185},{"decimal":"0.02","digital":"0:01:45","hours":0,"minutes":1,"name":"XML","percent":2.16,"seconds":45,"text":"1 min","total_seconds":105.433},{"decimal":"0.00","digital":"0:00:04","hours":0,"minutes":0,"name":"Bash","percent":0.09,"seconds":4,"text":"4 secs","total_seconds":4.555},{"decimal":"0.00","digital":"0:00:00","hours":0,"minutes":0,"name":"GitIgnore file","percent":0.01,"seconds":0,"text":"0 secs","total_seconds":0.638}],"machines":[{"decimal":"1.35","digital":"1:21:26","hours":1,"machine_name_id":"2cbe470f-1e60-4ef4-9ef5-fef2b41b0d83","minutes":21,"name":"DESKTOP-EQAREEK","percent":100,"seconds":26,"text":"1 hr 21 mins","total_seconds":4886.404}],"operating_systems":[{"decimal":"1.35","digital":"1:21:26","hours":1,"minutes":21,"name":"Windows","percent":100,"seconds":26,"text":"1 hr 21 mins","total_seconds":4886.404}],"projects":[{"color":null,"decimal":"1.30","digital":"1:18:00","hours":1,"minutes":18,"name":"mirai","percent":95.79,"seconds":0,"text":"1 hr 18 mins","total_seconds":4680.826},{"color":null,"decimal":"0.05","digital":"0:03:24","hours":0,"minutes":3,"name":"intellij-plugin","percent":4.19,"seconds":24,"text":"3 mins","total_seconds":204.94},{"color":null,"decimal":"0.00","digital":"0:00:00","hours":0,"minutes":0,"name":"Unknown Project","percent":0.01,"seconds":0,"text":"0 secs","total_seconds":0.638}],"range":{"date":"2023-04-01","end":"2023-04-01T15:59:59Z","start":"2023-03-31T16:00:00Z","text":"Sat Apr 1st 2023","timezone":"Asia/Shanghai"}}]