[
  {
    "languages": [
      {
        "name": "TypeScript",
        "total_seconds": 14486.310335,
        "digital": "4:01:26",
        "decimal": "4.02",
        "text": "4 hrs 1 min",
        "hours": 4,
        "minutes": 1,
        "seconds": 26,
        "percent": 95.25
      },
      {
        "name": "HTML",
        "total_seconds": 302.461622,
        "digital": "0:05:02",
        "decimal": "0.08",
        "text": "5 mins",
        "hours": 0,
        "minutes": 5,
        "seconds": 2,
        "percent": 1.99
      },
      {
        "name": "JavaScript",
        "total_seconds": 261.686373,
        "digital": "0:04:21",
        "decimal": "0.07",
        "text": "4 mins",
        "hours": 0,
        "minutes": 4,
        "seconds": 21,
        "percent": 1.72
      },
      {
        "name": "JSON",
        "total_seconds": 134.097147,
        "digital": "0:02:14",
        "decimal": "0.03",
        "text": "2 mins",
        "hours": 0,
        "minutes": 2,
        "seconds": 14,
        "percent": 0.88
      },
      {
        "name": "TSConfig",
        "total_seconds": 14.730595,
        "digital": "0:00:14",
        "decimal": "0.00",
        "text": "14 secs",
        "hours": 0,
        "minutes": 0,
        "seconds": 14,
        "percent": 0.1
      },
      {
        "name": "CSS",
        "total_seconds": 8.173765,
        "digital": "0:00:08",
        "decimal": "0.00",
        "text": "8 secs",
        "hours": 0,
        "minutes": 0,
        "seconds": 8,
        "percent": 0.05
      },
      {
        "name": "YAML",
        "total_seconds": 0.601236,
        "digital": "0:00:00",
        "decimal": "0.00",
        "text": "0 secs",
        "hours": 0,
        "minutes": 0,
        "seconds": 0,
        "percent": 0
      }
    ],
    "grand_total": {
      "hours": 4,
      "minutes": 13,
      "total_seconds": 15208.061073,
      "digital": "4:13",
      "decimal": "4.22",
      "text": "4 hrs 13 mins"
    },
    "editors": [
      {
        "name": "VS Code",
        "total_seconds": 15208.061073,
        "digital": "4:13:28",
        "decimal": "4.22",
        "text": "4 hrs 13 mins",
        "hours": 4,
        "minutes": 13,
        "seconds": 28,
        "percent": 100
      }
    ],
    "operating_systems": [
      {
        "name": "Windows",
        "total_seconds": 15208.061073,
        "digital": "4:13:28",
        "decimal": "4.22",
        "text": "4 hrs 13 mins",
        "hours": 4,
        "minutes": 13,
        "seconds": 28,
        "percent": 100
      }
    ],
    "categories": [
      {
        "name": "Coding",
        "total_seconds": 15208.061073,
        "digital": "4:13:28",
        "decimal": "4.22",
        "text": "4 hrs 13 mins",
        "hours": 4,
        "minutes": 13,
        "seconds": 28,
        "percent": 100
      }
    ],
    "dependencies": [
      {
        "name": "semi-ui",
        "total_seconds": 9777.538651,
        "digital": "2:42:57",
        "decimal": "2.70",
        "text": "2 hrs 42 mins",
        "hours": 2,
        "minutes": 42,
        "seconds": 57,
        "percent": 26.78
      },
      {
        "name": "api",
        "total_seconds": 6727.952289,
        "digital": "1:52:07",
        "decimal": "1.87",
        "text": "1 hr 52 mins",
        "hours": 1,
        "minutes": 52,
        "seconds": 7,
        "percent": 18.43
      },
      {
        "name": "scene-react",
        "total_seconds": 6727.952289,
        "digital": "1:52:07",
        "decimal": "1.87",
        "text": "1 hr 52 mins",
        "hours": 1,
        "minutes": 52,
        "seconds": 7,
        "percent": 18.43
      },
      {
        "name": "ThemeToggle",
        "total_seconds": 3018.676219,
        "digital": "0:50:18",
        "decimal": "0.83",
        "text": "50 mins",
        "hours": 0,
        "minutes": 50,
        "seconds": 18,
        "percent": 8.27
      },
      {
        "name": "VideoListPage",
        "total_seconds": 1068.482106,
        "digital": "0:17:48",
        "decimal": "0.28",
        "text": "17 mins",
        "hours": 0,
        "minutes": 17,
        "seconds": 48,
        "percent": 2.93
      },
      {
        "name": "react",
        "total_seconds": 740.850544,
        "digital": "0:12:20",
        "decimal": "0.20",
        "text": "12 mins",
        "hours": 0,
        "minutes": 12,
        "seconds": 20,
        "percent": 2.03
      },
      {
        "name": "lucide-react",
        "total_seconds": 559.936417,
        "digital": "0:09:19",
        "decimal": "0.15",
        "text": "9 mins",
        "hours": 0,
        "minutes": 9,
        "seconds": 19,
        "percent": 1.53
      },
      {
        "name": "useTheme",
        "total_seconds": 421.566632,
        "digital": "0:07:01",
        "decimal": "0.12",
        "text": "7 mins",
        "hours": 0,
        "minutes": 7,
        "seconds": 1,
        "percent": 1.15
      },
      {
        "name": "ThemeProvider",
        "total_seconds": 407.251588,
        "digital": "0:06:47",
        "decimal": "0.10",
        "text": "6 mins",
        "hours": 0,
        "minutes": 6,
        "seconds": 47,
        "percent": 1.12
      },
      {
        "name": "client",
        "total_seconds": 407.251588,
        "digital": "0:06:47",
        "decimal": "0.10",
        "text": "6 mins",
        "hours": 0,
        "minutes": 6,
        "seconds": 47,
        "percent": 1.12
      },
      {
        "name": "App",
        "total_seconds": 407.251588,
        "digital": "0:06:47",
        "decimal": "0.10",
        "text": "6 mins",
        "hours": 0,
        "minutes": 6,
        "seconds": 47,
        "percent": 1.12
      },
      {
        "name": "globals",
        "total_seconds": 380.170626,
        "digital": "0:06:20",
        "decimal": "0.10",
        "text": "6 mins",
        "hours": 0,
        "minutes": 6,
        "seconds": 20,
        "percent": 1.04
      },
      {
        "name": "normalize",
        "total_seconds": 373.278366,
        "digital": "0:06:13",
        "decimal": "0.10",
        "text": "6 mins",
        "hours": 0,
        "minutes": 6,
        "seconds": 13,
        "percent": 1.02
      },
      {
        "name": "meta",
        "total_seconds": 346.506279,
        "digital": "0:05:46",
        "decimal": "0.08",
        "text": "5 mins",
        "hours": 0,
        "minutes": 5,
        "seconds": 46,
        "percent": 0.95
      },
      {
        "name": "\"/src/main.tsx\"",
        "total_seconds": 302.461622,
        "digital": "0:05:02",
        "decimal": "0.08",
        "text": "5 mins",
        "hours": 0,
        "minutes": 5,
        "seconds": 2,
        "percent": 0.83
      },
      {
        "name": "Container",
        "total_seconds": 265.747433,
        "digital": "0:04:25",
        "decimal": "0.07",
        "text": "4 mins",
        "hours": 0,
        "minutes": 4,
        "seconds": 25,
        "percent": 0.73
      },
      {
        "name": "alova",
        "total_seconds": 226.807284,
        "digital": "0:03:46",
        "decimal": "0.05",
        "text": "3 mins",
        "hours": 0,
        "minutes": 3,
        "seconds": 46,
        "percent": 0.62
      },
      {
        "name": "vite",
        "total_seconds": 206.452195,
        "digital": "0:03:26",
        "decimal": "0.05",
        "text": "3 mins",
        "hours": 0,
        "minutes": 3,
        "seconds": 26,
        "percent": 0.57
      },
      {
        "name": "button",
        "total_seconds": 198.786282,
        "digital": "0:03:18",
        "decimal": "0.05",
        "text": "3 mins",
        "hours": 0,
        "minutes": 3,
        "seconds": 18,
        "percent": 0.54
      },
      {
        "name": "dropdown-menu",
        "total_seconds": 194.285692,
        "digital": "0:03:14",
        "decimal": "0.05",
        "text": "3 mins",
        "hours": 0,
        "minutes": 3,
        "seconds": 14,
        "percent": 0.53
      },
      {
        "name": "class-variance-authority",
        "total_seconds": 135.125139,
        "digital": "0:02:15",
        "decimal": "0.03",
        "text": "2 mins",
        "hours": 0,
        "minutes": 2,
        "seconds": 15,
        "percent": 0.37
      },
      {
        "name": "eslint",
        "total_seconds": 132.478083,
        "digital": "0:02:12",
        "decimal": "0.03",
        "text": "2 mins",
        "hours": 0,
        "minutes": 2,
        "seconds": 12,
        "percent": 0.36
      },
      {
        "name": "@vitejs/plugin-react",
        "total_seconds": 132.478083,
        "digital": "0:02:12",
        "decimal": "0.03",
        "text": "2 mins",
        "hours": 0,
        "minutes": 2,
        "seconds": 12,
        "percent": 0.36
      },
      {
        "name": "@typescript-eslint/eslint-plugin",
        "total_seconds": 132.478083,
        "digital": "0:02:12",
        "decimal": "0.03",
        "text": "2 mins",
        "hours": 0,
        "minutes": 2,
        "seconds": 12,
        "percent": 0.36
      },
      {
        "name": "@alova/scene-react",
        "total_seconds": 132.478083,
        "digital": "0:02:12",
        "decimal": "0.03",
        "text": "2 mins",
        "hours": 0,
        "minutes": 2,
        "seconds": 12,
        "percent": 0.36
      },
      {
        "name": "npm",
        "total_seconds": 132.478083,
        "digital": "0:02:12",
        "decimal": "0.03",
        "text": "2 mins",
        "hours": 0,
        "minutes": 2,
        "seconds": 12,
        "percent": 0.36
      },
      {
        "name": "tailwind-merge",
        "total_seconds": 132.478083,
        "digital": "0:02:12",
        "decimal": "0.03",
        "text": "2 mins",
        "hours": 0,
        "minutes": 2,
        "seconds": 12,
        "percent": 0.36
      },
      {
        "name": "eslint-plugin-react-hooks",
        "total_seconds": 132.478083,
        "digital": "0:02:12",
        "decimal": "0.03",
        "text": "2 mins",
        "hours": 0,
        "minutes": 2,
        "seconds": 12,
        "percent": 0.36
      },
      {
        "name": "@types/react",
        "total_seconds": 132.478083,
        "digital": "0:02:12",
        "decimal": "0.03",
        "text": "2 mins",
        "hours": 0,
        "minutes": 2,
        "seconds": 12,
        "percent": 0.36
      },
      {
        "name": "autoprefixer",
        "total_seconds": 132.478083,
        "digital": "0:02:12",
        "decimal": "0.03",
        "text": "2 mins",
        "hours": 0,
        "minutes": 2,
        "seconds": 12,
        "percent": 0.36
      },
      {
        "name": "eslint-plugin-react-refresh",
        "total_seconds": 132.478083,
        "digital": "0:02:12",
        "decimal": "0.03",
        "text": "2 mins",
        "hours": 0,
        "minutes": 2,
        "seconds": 12,
        "percent": 0.36
      },
      {
        "name": "postcss",
        "total_seconds": 132.478083,
        "digital": "0:02:12",
        "decimal": "0.03",
        "text": "2 mins",
        "hours": 0,
        "minutes": 2,
        "seconds": 12,
        "percent": 0.36
      },
      {
        "name": "@typescript-eslint/parser",
        "total_seconds": 132.478083,
        "digital": "0:02:12",
        "decimal": "0.03",
        "text": "2 mins",
        "hours": 0,
        "minutes": 2,
        "seconds": 12,
        "percent": 0.36
      },
      {
        "name": "react-dom",
        "total_seconds": 132.478083,
        "digital": "0:02:12",
        "decimal": "0.03",
        "text": "2 mins",
        "hours": 0,
        "minutes": 2,
        "seconds": 12,
        "percent": 0.36
      },
      {
        "name": "tailwindcss",
        "total_seconds": 132.478083,
        "digital": "0:02:12",
        "decimal": "0.03",
        "text": "2 mins",
        "hours": 0,
        "minutes": 2,
        "seconds": 12,
        "percent": 0.36
      },
      {
        "name": "typescript",
        "total_seconds": 132.478083,
        "digital": "0:02:12",
        "decimal": "0.03",
        "text": "2 mins",
        "hours": 0,
        "minutes": 2,
        "seconds": 12,
        "percent": 0.36
      },
      {
        "name": "clsx",
        "total_seconds": 132.478083,
        "digital": "0:02:12",
        "decimal": "0.03",
        "text": "2 mins",
        "hours": 0,
        "minutes": 2,
        "seconds": 12,
        "percent": 0.36
      },
      {
        "name": "@types/node",
        "total_seconds": 132.478083,
        "digital": "0:02:12",
        "decimal": "0.03",
        "text": "2 mins",
        "hours": 0,
        "minutes": 2,
        "seconds": 12,
        "percent": 0.36
      },
      {
        "name": "@douyinfe/semi-ui",
        "total_seconds": 132.478083,
        "digital": "0:02:12",
        "decimal": "0.03",
        "text": "2 mins",
        "hours": 0,
        "minutes": 2,
        "seconds": 12,
        "percent": 0.36
      },
      {
        "name": "@types/react-dom",
        "total_seconds": 132.478083,
        "digital": "0:02:12",
        "decimal": "0.03",
        "text": "2 mins",
        "hours": 0,
        "minutes": 2,
        "seconds": 12,
        "percent": 0.36
      },
      {
        "name": "tailwindcss-animate",
        "total_seconds": 127.783105,
        "digital": "0:02:07",
        "decimal": "0.03",
        "text": "2 mins",
        "hours": 0,
        "minutes": 2,
        "seconds": 7,
        "percent": 0.35
      },
      {
        "name": "card",
        "total_seconds": 123.358742,
        "digital": "0:02:03",
        "decimal": "0.03",
        "text": "2 mins",
        "hours": 0,
        "minutes": 2,
        "seconds": 3,
        "percent": 0.34
      },
      {
        "name": "pagination",
        "total_seconds": 123.358742,
        "digital": "0:02:03",
        "decimal": "0.03",
        "text": "2 mins",
        "hours": 0,
        "minutes": 2,
        "seconds": 3,
        "percent": 0.34
      },
      {
        "name": "PaginationData",
        "total_seconds": 94.329201,
        "digital": "0:01:34",
        "decimal": "0.02",
        "text": "1 min",
        "hours": 0,
        "minutes": 1,
        "seconds": 34,
        "percent": 0.26
      },
      {
        "name": "GlobalFetch",
        "total_seconds": 94.329201,
        "digital": "0:01:34",
        "decimal": "0.02",
        "text": "1 min",
        "hours": 0,
        "minutes": 1,
        "seconds": 34,
        "percent": 0.26
      },
      {
        "name": "plugin-react",
        "total_seconds": 73.974112,
        "digital": "0:01:13",
        "decimal": "0.02",
        "text": "1 min",
        "hours": 0,
        "minutes": 1,
        "seconds": 13,
        "percent": 0.2
      },
      {
        "name": "path",
        "total_seconds": 73.974112,
        "digital": "0:01:13",
        "decimal": "0.02",
        "text": "1 min",
        "hours": 0,
        "minutes": 1,
        "seconds": 13,
        "percent": 0.2
      },
      {
        "name": "@radix-ui/react-dropdown-menu",
        "total_seconds": 71.620655,
        "digital": "0:01:11",
        "decimal": "0.02",
        "text": "1 min",
        "hours": 0,
        "minutes": 1,
        "seconds": 11,
        "percent": 0.2
      },
      {
        "name": "@radix-ui/react-slot",
        "total_seconds": 71.620655,
        "digital": "0:01:11",
        "decimal": "0.02",
        "text": "1 min",
        "hours": 0,
        "minutes": 1,
        "seconds": 11,
        "percent": 0.2
      },
      {
        "name": "HolyGrail",
        "total_seconds": 66.535127,
        "digital": "0:01:06",
        "decimal": "0.02",
        "text": "1 min",
        "hours": 0,
        "minutes": 1,
        "seconds": 6,
        "percent": 0.18
      },
      {
        "name": "AppBar",
        "total_seconds": 66.535127,
        "digital": "0:01:06",
        "decimal": "0.02",
        "text": "1 min",
        "hours": 0,
        "minutes": 1,
        "seconds": 6,
        "percent": 0.18
      },
      {
        "name": "normalize.css",
        "total_seconds": 60.857428,
        "digital": "0:01:00",
        "decimal": "0.02",
        "text": "1 min",
        "hours": 0,
        "minutes": 1,
        "seconds": 0,
        "percent": 0.17
      },
      {
        "name": "utils",
        "total_seconds": 11.164012,
        "digital": "0:00:11",
        "decimal": "0.00",
        "text": "11 secs",
        "hours": 0,
        "minutes": 0,
        "seconds": 11,
        "percent": 0.03
      },
      {
        "name": "prop-types",
        "total_seconds": 9.389367,
        "digital": "0:00:09",
        "decimal": "0.00",
        "text": "9 secs",
        "hours": 0,
        "minutes": 0,
        "seconds": 9,
        "percent": 0.03
      },
      {
        "name": "interface",
        "total_seconds": 9.389367,
        "digital": "0:00:09",
        "decimal": "0.00",
        "text": "9 secs",
        "hours": 0,
        "minutes": 0,
        "seconds": 9,
        "percent": 0.03
      },
      {
        "name": "type",
        "total_seconds": 9.389367,
        "digital": "0:00:09",
        "decimal": "0.00",
        "text": "9 secs",
        "hours": 0,
        "minutes": 0,
        "seconds": 9,
        "percent": 0.03
      },
      {
        "name": "constants",
        "total_seconds": 9.389367,
        "digital": "0:00:09",
        "decimal": "0.00",
        "text": "9 secs",
        "hours": 0,
        "minutes": 0,
        "seconds": 9,
        "percent": 0.03
      },
      {
        "name": "react-slot",
        "total_seconds": 2.647056,
        "digital": "0:00:02",
        "decimal": "0.00",
        "text": "2 secs",
        "hours": 0,
        "minutes": 0,
        "seconds": 2,
        "percent": 0.01
      },
      {
        "name": "react-dropdown-menu",
        "total_seconds": 1.391112,
        "digital": "0:00:01",
        "decimal": "0.00",
        "text": "1 sec",
        "hours": 0,
        "minutes": 0,
        "seconds": 1,
        "percent": 0
      }
    ],
    "machines": [
      {
        "name": "meng",
        "total_seconds": 15208.061073,
        "machine_name_id": "018d30bd-b558-4484-8a5f-1a2425d89e4a",
        "digital": "4:13:28",
        "decimal": "4.22",
        "text": "4 hrs 13 mins",
        "hours": 4,
        "minutes": 13,
        "seconds": 28,
        "percent": 100
      }
    ],
    "projects": [
      {
        "name": "fc2-service",
        "total_seconds": 15208.061073,
        "digital": "4:13:28",
        "decimal": "4.22",
        "text": "4 hrs 13 mins",
        "hours": 4,
        "minutes": 13,
        "seconds": 28,
        "percent": 100
      }
    ],
    "range": {
      "start": "2024-01-22T16:00:00Z",
      "end": "2024-01-23T15:59:59Z",
      "date": "2024-01-23",
      "text": "Tue Jan 23rd 2024",
      "timezone": "Asia/Shanghai"
    }
  }
]
